{
  "title": "LONGEMBED: Extending Embedding Models for Long Context Retrieval",
  "authors": [
    "Dawei Zhu",
    "Liang Wang",
    "Nan Yang",
    "Yifan Song",
    "Wenhao Wu",
    "Furu Wei",
    "Sujian Li"
  ],
  "languages": [
    "English"
  ],
  "research_areas": [
    "T08 Evaluation, Validation, Quality Assurance and Benchmarking Methodologies",
    "T10 Question Answering, Open-domain question answering, closed-domain question answering, extractive and abstractive QA, multi-hop question answering",
    "T18 Text Summarization"
  ],
  "paper_id": "2024.emnlp-main.47",
  "acl_url": "https://aclanthology.org/2024.emnlp-main.47/"
}