{
  "title": "Cultural Conditioning or Placebo? On the Effectiveness of Socio-Demographic Prompting",
  "authors": [
    "Sagnik Mukherjee",
    "Muhammad Farid Adilazuarda",
    "Sunayana Sitaram",
    "Kalika Bali",
    "Alham Fikri Aji",
    "Monojit Choudhury"
  ],
  "languages": [
    "English"
  ],
  "research_areas": [
    "T08 Evaluation, Validation, Quality Assurance and Benchmarking Methodologies",
    "T01 Bias, Guardrails, filters",
    "T14 Language Modeling (including training, fine-tuning, representation learning, and generation of synthetic data)"
  ],
  "paper_id": "2024.emnlp-main.884",
  "acl_url": "https://aclanthology.org/2024.emnlp-main.884/"
}