{
  "title": "Can Large Language Models Always Solve Easy Problems if They Can Solve Harder Ones?",
  "authors": [
    "Zhe Yang",
    "Yichang Zhang",
    "Tianyu Liu",
    "Jian Yang",
    "Junyang Lin",
    "Chang Zhou",
    "Zhifang Sui"
  ],
  "languages": [
    "English"
  ],
  "research_areas": [
    "T08 Evaluation, Validation, Quality Assurance and Benchmarking Methodologies",
    "T27 Code generation and programming languages",
    "T19 Text Simplification, Plain Language and Assistive Technologies"
  ],
  "paper_id": "2024.emnlp-main.92",
  "acl_url": "https://aclanthology.org/2024.emnlp-main.92/"
}