{
  "title": "Stepwise Verification and Remediation of Student Reasoning Errors with Large Language Model Tutors",
  "authors": [
    "Nico Daheim",
    "Jakub Macina",
    "Manu Kapur",
    "Iryna Gurevych",
    "Mrinmaya Sachan"
  ],
  "languages": [
    "English"
  ],
  "research_areas": [
    "T29 NLP for education, Automated essay scoring and feedback generation, grammatical error correction and detection, intelligent tutoring systems"
  ],
  "paper_id": "2024.emnlp-main.478",
  "acl_url": "https://aclanthology.org/2024.emnlp-main.478/"
}