{
  "title": "A Survey on In-context Learning",
  "authors": [
    "Qingxiu Dong",
    "Lei Li",
    "Damai Dai",
    "Ce Zheng",
    "Jingyuan Ma",
    "Rui Li",
    "Heming Xia",
    "Jingjing Xu",
    "Zhiyong Wu",
    "Baobao Chang",
    "Xu Sun",
    "Lei Li",
    "Zhifang Sui"
  ],
  "languages": [
    "English"
  ],
  "research_areas": [
    "T14 Language Modeling",
    "T08 Evaluation, Validation, Quality Assurance and Benchmarking Methodologies",
    "T09 Inference and Reasoning"
  ],
  "paper_id": "2024.emnlp-main.64",
  "acl_url": "https://aclanthology.org/2024.emnlp-main.64/"
}