{
  "title": "UNO Arena for Evaluating Sequential Decision-Making Capability of Large Language Models",
  "authors": [
    "Zhan Yue Qin",
    "Haochuan Wang",
    "Deyuan Liu",
    "Ziyang Song",
    "Cunhang Fan",
    "Zhao Lv",
    "Jinlin Wu",
    "Zhen Lei",
    "Zhiying Tu",
    "Dianhui Chu",
    "Xiaoyan Yu",
    "Dianbo Sui"
  ],
  "languages": [
    "English"
  ],
  "research_areas": [
    "T08 Evaluation, Validation, Quality Assurance and Benchmarking Methodologies",
    "T14 Language Modeling (including training, fine-tuning, representation learning, and generation of synthetic data)",
    "T09 Inference and Reasoning"
  ],
  "paper_id": "2024.emnlp-main.435",
  "acl_url": "https://aclanthology.org/2024.emnlp-main.435/"
}