{
  "title": "You May Like This Hotel Because ...: Identifying Evidence for Explainable Recommendations",
  "authors": [
    "Shin Kanouchi",
    "Masato Neishi",
    "Yuta Hayashibe",
    "Hiroki Ouchi",
    "Naoaki Okazaki"
  ],
  "languages": [
    "English"
  ],
  "research_areas": [
    "T12 Interpretability/explainability of language models and language and speech processing tools",
    "T20 Opinion & Argument Mining, Offensive Language/ Hate speech/ Toxic Language Detection, Sentiment Analysis, Emotion Recognition/Generation"
  ],
  "paper_id": "2020.aacl-main.89",
  "acl_url": "https://aclanthology.org/2020.aacl-main.89/"
}