{
  "title": "Automatic Generation of Model and Data Cards: A Step Towards Responsible AI",
  "authors": [
    "Jiarui Liu",
    "Wenkai Li",
    "Zhijing Jin",
    "Mona Diab"
  ],
  "languages": [
    "English"
  ],
  "research_areas": [
    "T08 Evaluation, Validation, Quality Assurance and Benchmarking Methodologies",
    "T12 Interpretability/explainability of language models and language and speech processing tools",
    "T27 Code generation and programming languages"
  ],
  "paper_id": "2024.naacl-long.110",
  "acl_url": "https://aclanthology.org/2024.naacl-long.110/"
}