{
  "title": "Towards Understanding Sample Variance in Visually Grounded Language Generation: Evaluations and Observations",
  "authors": [
    "Wanrong Zhu",
    "Xin Eric Wang",
    "Pradyumna Narayana",
    "Kazoo Sone",
    "Sugato Basu",
    "William Yang Wang"
  ],
  "languages": [
    "English",
    "Chinese"
  ],
  "research_areas": [
    "T17 Multimodality, Cross-modality (including Sign Languages, Vision and Other Modalities), Multimodal Applications, Grounded Language Acquisition",
    "T08 Evaluation, Validation, Quality Assurance and Benchmarking Methodologies"
  ],
  "paper_id": "2020.emnlp-main.708",
  "acl_url": "https://aclanthology.org/2020.emnlp-main.708/"
}