{
  "title": "CoPHE: A Count-Preserving Hierarchical Evaluation Metric in Large-Scale Multi-Label Text Classification",
  "authors": [
    "Matúš Falis",
    "Hang Dong",
    "Alexandra Birch",
    "Beatrice Alex"
  ],
  "languages": [
    "English"
  ],
  "research_areas": [
    "T13 Knowledge discovery/representation (knowledge graphs, linked data, terminologies, lexicons, ontologies, etc.)",
    "T08 Evaluation, Validation, Quality Assurance and Benchmarking Methodologies"
  ],
  "paper_id": "2021.emnlp-main.69",
  "acl_url": "https://aclanthology.org/2021.emnlp-main.69/"
}