{
  "title": "Focus on what matters: Applying Discourse Coherence Theory to Cross Document Coreference",
  "authors": [
    "William Held",
    "Dan Iter",
    "Dan Jurafsky"
  ],
  "languages": [
    "English"
  ],
  "research_areas": [
    "T11 Information Extraction, Named Entity Recognition, Relationship Extraction and Event Detection",
    "T14 Language Modeling (including training, fine-tuning, representation learning, and generation of synthetic data)",
    "T15 Lexicon and Semantics"
  ],
  "paper_id": "2021.emnlp-main.106",
  "acl_url": "https://aclanthology.org/2021.emnlp-main.106/"
}