{
  "title": "Social Orientation: A New Feature for Dialogue Analysis",
  "authors": [
    "Todd Morrill",
    "Zhaoyuan Deng",
    "Yanda Chen",
    "Amith Ananthram",
    "Colin Wayne Leach",
    "Kathleen McKeown"
  ],
  "languages": [
    "English",
    "Chinese"
  ],
  "research_areas": [
    "T03 Dialogue, Conversational Systems, Chatbots, Human-Robot Interaction",
    "T12 Interpretability/explainability of language models and language and speech processing tools",
    "T22 Psycholinguistics, Cognitive Linguistics and Linguistic Theories"
  ],
  "paper_id": "2024.lrec-main.1304",
  "acl_url": "https://aclanthology.org/2024.lrec-main.1304/"
}