{
  "title": "The Slovak Autistic and Non-Autistic Child Speech Corpus: Task-Oriented Child-Adult Interactions",
  "authors": [
    "Joanna Kruyt",
    "Katarína Polóniová",
    "Róbert Sabo",
    "Daniela Ostatníková",
    "Štefan Beňuš"
  ],
  "languages": [
    "Slovak"
  ],
  "research_areas": [
    "T24 Speech Resources and Processing",
    "T22 Psycholinguistics, Cognitive Linguistics and Linguistic Theories"
  ],
  "paper_id": "2024.lrec-main.1399",
  "acl_url": "https://aclanthology.org/2024.lrec-main.1399/"
}