{
  "title": "ÌròyìnSpeech: A multi-purpose Yorùbá Speech Corpus",
  "authors": [
    "Tolúlopé Ógúnrèmí",
    "Kólá Túbòsún",
    "Anuoluwapo Aremu",
    "Iroro Orife",
    "David Ifeoluwa Adelani"
  ],
  "languages": [
    "Yorùbá"
  ],
  "research_areas": [
    "T24 Speech Resources and Processing",
    "T14 Language Modeling",
    "T22 Psycholinguistics, Cognitive Linguistics and Linguistic Theories"
  ],
  "paper_id": "2024.lrec-main.812",
  "acl_url": "https://aclanthology.org/2024.lrec-main.812/"
}