{
  "title": "JaParaPat: A Large-Scale Japanese-English Parallel Patent Application Corpus",
  "authors": [
    "Masaaki Nagata",
    "Makoto Morishita",
    "Katsuki Chousa",
    "Norihito Yasuda"
  ],
  "languages": [
    "Japanese",
    "English"
  ],
  "research_areas": [
    "T02 Corpora, Treebanks and Annotation; Tools, Systems and Platforms",
    "T16 Machine Translation (including Speech-to-Speech) and Translation Aids"
  ],
  "paper_id": "2024.lrec-main.826",
  "acl_url": "https://aclanthology.org/2024.lrec-main.826/"
}