{
  "title": "Predictive and Distinctive Linguistic Features in Schizophrenia-Bipolar Spectrum Disorders",
  "authors": [
    "Martina Katalin Szabó",
    "Veronika Vincze",
    "Bernadett Dam",
    "Csenge Guba",
    "Anita Bagi",
    "István Szendi"
  ],
  "languages": [
    "Hungarian"
  ],
  "research_areas": [
    "T26 Clinical/biomedical NLP, NLP for Mental Health and Wellbeing",
    "T21 Parsing, Tagging, Chunking, Grammar, Syntax, Morphosyntax, Morphology",
    "T15 Lexicon and Semantics"
  ],
  "paper_id": "2024.lrec-main.1133",
  "acl_url": "https://aclanthology.org/2024.lrec-main.1133/"
}