{
  "title": "Towards Standardized Annotation and Parsing for Korean FrameNet",
  "authors": [
    "Yige Chen",
    "Jae Ihn",
    "KyungTae Lim",
    "Jungyeul Park"
  ],
  "languages": [
    "Korean"
  ],
  "research_areas": [
    "T21 Parsing, Tagging, Chunking, Grammar, Syntax, Morphosyntax, Morphology",
    "T15 Lexicon and Semantics",
    "T02 Corpora, Treebanks and Annotation; Tools, Systems and Platforms"
  ],
  "paper_id": "2024.lrec-main.1447",
  "acl_url": "https://aclanthology.org/2024.lrec-main.1447/"
}