{
  "title": "Unifying Dual-Space Embedding for Entity Alignment via Contrastive Learning",
  "authors": [
    "Cunda Wang",
    "Weihua Wang",
    "Qiuyu Liang",
    "Feilong Bao",
    "Guanglai Gao"
  ],
  "languages": [
    "English",
    "French",
    "German"
  ],
  "research_areas": [
    "T13 Knowledge discovery/representation (knowledge graphs, linked data, terminologies, lexicons, ontologies, etc.)"
  ],
  "paper_id": "2025.coling-main.209",
  "acl_url": "https://aclanthology.org/2025.coling-main.209/"
}