{
  "title": "InstructGEC: Enhancing Unsupervised Grammatical Error Correction with Instruction Tuning",
  "authors": [
    "Jiayi Deng",
    "Chen Chen",
    "Chunyan Hou",
    "Xiaojie Yuan"
  ],
  "languages": [
    "Chinese",
    "English"
  ],
  "research_areas": [
    "T29 NLP for education, Automated essay scoring and feedback generation, grammatical error correction and detection, intelligent tutoring systems"
  ],
  "paper_id": "2025.coling-main.9",
  "acl_url": "https://aclanthology.org/2025.coling-main.9/"
}