{
  "title": "Data Augmentation with Paraphrase Generation and Entity Extraction for Multimodal Dialogue System",
  "authors": [
    "Eda Okur",
    "Saurav Sahay",
    "Lama Nachman"
  ],
  "languages": [
    "English"
  ],
  "research_areas": [
    "T03 Dialogue, Conversational Systems, Chatbots, Human-Robot Interaction",
    "T14 Language Modeling (including training, fine-tuning, representation learning, and generation of synthetic data)",
    "T11 Information Extraction, Named Entity Recognition, Relationship Extraction and Event Detection"
  ],
  "paper_id": "2022.lrec-1.437",
  "acl_url": "https://aclanthology.org/2022.lrec-1.437/"
}