{
  "title": "Annotation-Scheme Reconstruction for \"Fake News\" and Japanese Fake News Dataset",
  "authors": [
    "Taichi Murayama",
    "Shohei Hisada",
    "Makoto Uehara",
    "Shoko Wakamiya",
    "Eiji Aramaki"
  ],
  "languages": [
    "Japanese"
  ],
  "research_areas": [
    "T02 Corpora, Treebanks and Annotation; Tools, Systems and Platforms",
    "T23 Social Media Processing",
    "T20 Opinion & Argument Mining, Offensive Language/ Hate speech/ Toxic Language Detection, Sentiment Analysis, Emotion Recognition/Generation"
  ],
  "paper_id": "2022.lrec-1.784",
  "acl_url": "https://aclanthology.org/2022.lrec-1.784/"
}