{
  "title": "Fine-Grained Error Analysis and Fair Evaluation of Labeled Spans",
  "authors": [
    "Katrin Ortmann"
  ],
  "languages": [
    "German"
  ],
  "research_areas": [
    "T08 Evaluation, Validation, Quality Assurance and Benchmarking Methodologies",
    "T11 Information Extraction, Named Entity Recognition, Relationship Extraction and Event Detection",
    "T21 Parsing, Tagging, Chunking, Grammar, Syntax, Morphosyntax, Morphology"
  ],
  "paper_id": "2022.lrec-1.150",
  "acl_url": "https://aclanthology.org/2022.lrec-1.150/"
}