{
  "title": "Domain Adaptation in Neural Machine Translation using a Qualia-Enriched FrameNet",
  "authors": [
    "Alexandre Diniz Costa",
    "Mateus Coutinho Marim",
    "Ely Edison da Silva Matos",
    "Tiago Timponi Torrent"
  ],
  "languages": [
    "Portuguese",
    "English"
  ],
  "research_areas": [
    "T13 Knowledge discovery/representation (knowledge graphs, linked data, terminologies, lexicons, ontologies, etc.)",
    "T16 Machine Translation (including Speech-to-Speech) and Translation Aids"
  ],
  "paper_id": "2022.lrec-1.1",
  "acl_url": "https://aclanthology.org/2022.lrec-1.1/"
}