{
  "title": "The PALMA Corpora of African Varieties of Portuguese",
  "authors": [
    "Tjerk Hagemeyer",
    "Amália Mendes",
    "Rita Gonçalves",
    "Catarina Cornejo",
    "Raquel Madureira",
    "Michel Généreux"
  ],
  "languages": [
    "Portuguese"
  ],
  "research_areas": [
    "T02 Corpora, Treebanks and Annotation; Tools, Systems and Platforms",
    "T21 Parsing, Tagging, Chunking, Grammar, Syntax, Morphosyntax, Morphology",
    "T15 Lexicon and Semantics"
  ],
  "paper_id": "2022.lrec-1.539",
  "acl_url": "https://aclanthology.org/2022.lrec-1.539/"
}