{
  "title": "Clarifying Implicit and Underspecified Phrases in Instructional Text",
  "authors": [
    "Talita Anthonio",
    "Anna Sauer",
    "Michael Roth"
  ],
  "languages": [
    "English"
  ],
  "research_areas": [
    "T14 Language Modeling (including training, fine-tuning, representation learning, and generation of synthetic data)",
    "T15 Lexicon and Semantics",
    "T02 Corpora, Treebanks and Annotation; Tools, Systems and Platforms"
  ],
  "paper_id": "2022.lrec-1.354",
  "acl_url": "https://aclanthology.org/2022.lrec-1.354/"
}