{
  "title": "Probe-Less Probing of BERT's Layer-Wise Linguistic Knowledge with Masked Word Prediction",
  "authors": [
    "Tatsuya Aoyama",
    "Nathan Schneider"
  ],
  "languages": [
    "English"
  ],
  "research_areas": [
    "T12 Interpretability/explainability of language models and language and speech processing tools",
    "T21 Parsing, Tagging, Chunking, Grammar, Syntax, Morphosyntax, Morphology"
  ],
  "paper_id": "2022.naacl-srw.25",
  "acl_url": "https://aclanthology.org/2022.naacl-srw.25/"
}