{
  "title": "Combining Humor and Sarcasm for Improving Political Parody Detection",
  "authors": [
    "Xiao Ao",
    "Danae Sánchez Villegas",
    "Daniel Preotiuc-Pietro",
    "Nikolaos Aletras"
  ],
  "languages": [
    "English"
  ],
  "research_areas": [
    "T23 Social Media Processing",
    "T20 Opinion & Argument Mining, Offensive Language/ Hate speech/ Toxic Language Detection, Sentiment Analysis, Emotion Recognition/Generation"
  ],
  "paper_id": "2022.naacl-main.131",
  "acl_url": "https://aclanthology.org/2022.naacl-main.131/"
}