{
  "title": "JointLK: Joint Reasoning with Language Models and Knowledge Graphs for Commonsense Question Answering",
  "authors": [
    "Yueqing Sun",
    "Qi Shi",
    "Le Qi",
    "Yu Zhang"
  ],
  "languages": [
    "English"
  ],
  "research_areas": [
    "T10 Question Answering, Open-domain question answering, closed-domain question answering, extractive and abstractive QA, multi-hop question answering",
    "T13 Knowledge discovery/representation (knowledge graphs, linked data, terminologies, lexicons, ontologies, etc.)",
    "T12 Interpretability/explainability of language models and language and speech processing tools"
  ],
  "paper_id": "2022.naacl-main.372",
  "acl_url": "https://aclanthology.org/2022.naacl-main.372/"
}