{
  "title": "Negation-Instance Based Evaluation of End-to-End Negation Resolution",
  "authors": [
    "Elizaveta Sineva",
    "Stefan Grunewald",
    "Annemarie Friedrich",
    "Jonas Kuhn"
  ],
  "languages": [
    "English"
  ],
  "research_areas": [
    "T08 Evaluation, Validation, Quality Assurance and Benchmarking Methodologies",
    "T21 Parsing, Tagging, Chunking, Grammar, Syntax, Morphosyntax, Morphology"
  ],
  "paper_id": "2021.conll-1.41",
  "acl_url": "https://aclanthology.org/2021.conll-1.41/"
}