{
  "title": "C³: A Bilingual Benchmark for Spoken Dialogue Models Exploring Challenges in Complex Conversations",
  "authors": [
    "Chengqian Ma",
    "Wei Tao",
    "Yiwen Guo"
  ],
  "languages": [
    "Chinese",
    "English"
  ],
  "research_areas": [
    "T03 Dialogue, Conversational Systems, Chatbots, Human-Robot Interaction",
    "T24 Speech Resources and Processing (including Phonetic Databases, Phonology, Prosody, Speech Recognition, Synthesis and Spoken Language Understanding)",
    "T08 Evaluation, Validation, Quality Assurance and Benchmarking Methodologies"
  ],
  "paper_id": "2025.emnlp-main.1160",
  "acl_url": "https://aclanthology.org/2025.emnlp-main.1160/"
}