{
  "title": "From Automation to Autonomy: A Survey on Large Language Models in Scientific Discovery",
  "authors": [
    "Tianshi Zheng",
    "Zheye Deng",
    "Hong Ting Tsang",
    "Weiqi Wang",
    "Jiaxin Bai",
    "Zihao Wang",
    "Yangqiu Song"
  ],
  "languages": [],
  "research_areas": [
    "T08 Evaluation, Validation, Quality Assurance and Benchmarking Methodologies",
    "T12 Interpretability/explainability of language models and language and speech processing tools",
    "T13 Knowledge discovery/representation (knowledge graphs, linked data, terminologies, lexicons, ontologies, etc.)"
  ],
  "paper_id": "2025.emnlp-main.895",
  "acl_url": "https://aclanthology.org/2025.emnlp-main.895/"
}