{
  "title": "Separate the Wheat from the Chaff: Winnowing Down Divergent Views in Retrieval Augmented Generation",
  "authors": [
    "Song Wang",
    "Zihan Chen",
    "Peng Wang",
    "Zhepei Wei",
    "Zhen Tan",
    "Yu Meng",
    "Cong Shen",
    "Jundong Li"
  ],
  "languages": [
    "English"
  ],
  "research_areas": [
    "T10 Question Answering, Open-domain question answering, closed-domain question answering, extractive and abstractive QA, multi-hop question answering",
    "T06 Information Retrieval and Cross-lingual Retrieval",
    "T09 Inference and Reasoning"
  ],
  "paper_id": "2025.emnlp-main.587",
  "acl_url": "https://aclanthology.org/2025.emnlp-main.587/"
}