{
  "title": "Neural Topic Modeling via Contextual and Graph Information Fusion",
  "authors": [
    "Jiyuan Liu",
    "Jiaxing Yan",
    "Chunjiang Zhu",
    "Xingyu Liu",
    "Qing Li",
    "Yanghui Rao"
  ],
  "languages": [
    "English"
  ],
  "research_areas": [
    "T12 Interpretability/explainability of language models and language and speech processing tools",
    "T13 Knowledge discovery/representation (knowledge graphs, linked data, terminologies, lexicons, ontologies, etc.)"
  ],
  "paper_id": "2025.emnlp-main.670",
  "acl_url": "https://aclanthology.org/2025.emnlp-main.670/"
}