{
  "title": "How Hate Speech Varies by Target Identity: A Computational Analysis",
  "authors": [
    "Michael Miller Yoder",
    "Lynnette Hui Xian Ng",
    "David West Brown",
    "Kathleen M. Carley"
  ],
  "languages": [
    "English"
  ],
  "research_areas": [
    "T20 Opinion & Argument Mining, Offensive Language/ Hate speech/ Toxic Language Detection, Sentiment Analysis, Emotion Recognition/Generation",
    "T23 Social Media Processing"
  ],
  "paper_id": "2022.conll-1.3",
  "acl_url": "https://aclanthology.org/2022.conll-1.3/"
}