{
  "title": "Multi-task Learning of Spoken Language Understanding by Integrating N-Best Hypotheses with Hierarchical Attention",
  "authors": [
    "Mingda Li",
    "Xinyue Liu",
    "Weitong Ruan",
    "Luca Soldaini",
    "Wael Hamza",
    "Chengwei Su"
  ],
  "languages": [
    "English"
  ],
  "research_areas": [
    "T24 Speech Resources and Processing (including Phonetic Databases, Phonology, Prosody, Speech Recognition, Synthesis and Spoken Language Understanding)"
  ],
  "paper_id": "2020.coling-industry.11",
  "acl_url": "https://aclanthology.org/2020.coling-industry.11/"
}