{
  "title": "ArchBERT: Bi-Modal Understanding of Neural Architectures and Natural Languages",
  "authors": [
    "Mohammad Akbari",
    "Saeed Ranjbar Alvar",
    "Behnam Kamranian",
    "Amin Banitalebi-Dehkordi",
    "Yong Zhang"
  ],
  "languages": [
    "English"
  ],
  "research_areas": [
    "T17 Multimodality, Cross-modality (including Sign Languages, Vision and Other Modalities), Multimodal Applications, Grounded Language Acquisition",
    "T10 Question Answering, Open-domain question answering, closed-domain question answering, extractive and abstractive QA, multi-hop question answering",
    "T14 Language Modeling (including training, fine-tuning, representation learning, and generation of synthetic data)"
  ],
  "paper_id": "2023.conll-1.7",
  "acl_url": "https://aclanthology.org/2023.conll-1.7/"
}