{
  "title": "Engagement Undermines Safety: How Stereotypes and Toxicity Shape Humor in Language Models",
  "authors": [
    "Atharvan Dogra",
    "Soumya Suvra Ghosal",
    "Ameet Deshpande",
    "Ashwin Kalyan",
    "Dinesh Manocha"
  ],
  "languages": [
    "English"
  ],
  "research_areas": [
    "T01 Bias, Guardrails, filters",
    "T08 Evaluation, Validation, Quality Assurance and Benchmarking Methodologies",
    "T20 Opinion & Argument Mining, Offensive Language/ Hate speech/ Toxic Language Detection, Sentiment Analysis, Emotion Recognition/Generation"
  ],
  "paper_id": "2026.eacl-long.373",
  "acl_url": "https://aclanthology.org/2026.eacl-long.373/"
}