{
  "title": "Enhancing User Safety: Context-Aware Detection of Offensive Query-Ad Pairs in Multimodal Search Advertising",
  "authors": [
    "Gaurav Kumar",
    "Qiangjian Xi",
    "Tanmaya Shekhar Dabral",
    "Hooshang Ghasemi",
    "Abishek Krishnamoorthy",
    "Danqing Fu",
    "Rui Min",
    "Emilio Antunez",
    "Zhongli Ding",
    "Pradyumna Narayana"
  ],
  "languages": [
    "English"
  ],
  "research_areas": [
    "T01 Bias, Guardrails, filters",
    "T17 Multimodality, Cross-modality (including Sign Languages, Vision and Other Modalities), Multimodal Applications, Grounded Language Acquisition",
    "T20 Opinion & Argument Mining, Offensive Language/ Hate speech/ Toxic Language Detection, Sentiment Analysis, Emotion Recognition/Generation"
  ],
  "paper_id": "2026.eacl-industry.36",
  "acl_url": "https://aclanthology.org/2026.eacl-industry.36/"
}