{
  "title": "Specialization through Collaboration: Understanding Expert Interaction in Mixture-of-Expert Large Language Models",
  "authors": [
    "Yuanbo Tang",
    "Yan Tang",
    "Naifan Zhang",
    "Meixuan Chen",
    "Yang Li"
  ],
  "languages": [
    "English"
  ],
  "research_areas": [
    "T12 Interpretability/explainability of language models and language and speech processing tools",
    "T14 Language Modeling (including training, fine-tuning, representation learning, and generation of synthetic data)"
  ],
  "paper_id": "2026.eacl-long.104",
  "acl_url": "https://aclanthology.org/2026.eacl-long.104/"
}