{
  "title": "NL-EDIT: Correcting Semantic Parse Errors through Natural Language Interaction",
  "authors": [
    "Ahmed Elgohary",
    "Christopher Meek",
    "Matthew Richardson",
    "Adam Fourney",
    "Gonzalo Ramos",
    "Ahmed Hassan Awadallah"
  ],
  "languages": [
    "English"
  ],
  "research_areas": [
    "T12 Interpretability/explainability of language models and language and speech processing tools",
    "T21 Parsing, Tagging, Chunking, Grammar, Syntax, Morphosyntax, Morphology",
    "T29 NLP for education, Automated essay scoring and feedback generation, grammatical error correction and detection, intelligent tutoring systems"
  ],
  "paper_id": "2021.naacl-main.444",
  "acl_url": "https://aclanthology.org/2021.naacl-main.444/"
}