{
  "title": "MTAG: Modal-Temporal Attention Graph for Unaligned Human Multimodal Language Sequences",
  "authors": [
    "Jianing Yang",
    "Yongxin Wang",
    "Ruitao Yi",
    "Yuying Zhu",
    "Azaan Rehman",
    "Amir Zadeh",
    "Soujanya Poria",
    "Louis-Philippe Morency"
  ],
  "languages": [
    "English"
  ],
  "research_areas": [
    "T17 Multimodality, Cross-modality (including Sign Languages, Vision and Other Modalities), Multimodal Applications, Grounded Language Acquisition",
    "T20 Opinion & Argument Mining, Offensive Language/ Hate speech/ Toxic Language Detection, Sentiment Analysis, Emotion Recognition/Generation"
  ],
  "paper_id": "2021.naacl-main.79",
  "acl_url": "https://aclanthology.org/2021.naacl-main.79/"
}