{
  "title": "Graph-Assisted Culturally Adaptable Idiomatic Translation for Indic Languages",
  "authors": [
    "Pratik Rakesh Singh",
    "Kritarth Prasad",
    "Mohammadi Zaki",
    "Pankaj Wasnik"
  ],
  "languages": [
    "English",
    "Hindi",
    "Bengali",
    "Tamil",
    "Telugu"
  ],
  "research_areas": [
    "T16 Machine Translation (including Speech-to-Speech) and Translation Aids",
    "T13 Knowledge discovery/representation (knowledge graphs, linked data, terminologies, lexicons, ontologies, etc.)",
    "T08 Evaluation, Validation, Quality Assurance and Benchmarking Methodologies"
  ],
  "paper_id": "2025.findings-acl.367",
  "acl_url": "https://aclanthology.org/2025.findings-acl.367/"
}