{
  "title": "Listening to Patients: Detecting and Mitigating Patient Misreport in Medical Dialogue System",
  "authors": [
    "Lang Qin",
    "Yao Zhang",
    "Hongru Liang",
    "Adam Jatowt",
    "Zhenglu Yang"
  ],
  "languages": [
    "Chinese",
    "English"
  ],
  "research_areas": [
    "T03 Dialogue, Conversational Systems, Chatbots, Human-Robot Interaction",
    "T13 Knowledge discovery/representation (knowledge graphs, linked data, terminologies, lexicons, ontologies, etc.)",
    "T26 Clinical/biomedical NLP, NLP for Mental Health and Wellbeing"
  ],
  "paper_id": "2025.findings-acl.135",
  "acl_url": "https://aclanthology.org/2025.findings-acl.135/"
}