{
  "title": "ToolSpectrum: Towards Personalized Tool Utilization for Large Language Models",
  "authors": [
    "Zihao Cheng",
    "Hongru Wang",
    "Zeming Liu",
    "Yuhang Guo",
    "Yuanfang Guo",
    "Yunhong Wang",
    "Haifeng Wang"
  ],
  "languages": [
    "English"
  ],
  "research_areas": [
    "T08 Evaluation, Validation, Quality Assurance and Benchmarking Methodologies",
    "T12 Interpretability/explainability of language models and language and speech processing tools",
    "T29 NLP for education, Automated essay scoring and feedback generation, grammatical error correction and detection, intelligent tutoring systems"
  ],
  "paper_id": "2025.findings-acl.1063",
  "acl_url": "https://aclanthology.org/2025.findings-acl.1063/"
}