{
  "title": "A Fully Automated Pipeline for Conversational Discourse Annotation: Tree Scheme Generation and Labeling with Large Language Models",
  "authors": [
    "Kseniia Petukhova",
    "Ekaterina Kochmar"
  ],
  "languages": [
    "English"
  ],
  "research_areas": [
    "T02 Corpora, Treebanks and Annotation; Tools, Systems and Platforms",
    "T03 Dialogue, Conversational Systems, Chatbots, Human-Robot Interaction",
    "T05 Discourse and Pragmatics"
  ],
  "paper_id": "2025.findings-acl.818",
  "acl_url": "https://aclanthology.org/2025.findings-acl.818/"
}