{
  "title": "R³Mem: Bridging Memory Retention and Retrieval via Reversible Compression",
  "authors": [
    "Xiaoqiang Wang",
    "Suyuchen Wang",
    "Yun Zhu",
    "Bang Liu"
  ],
  "languages": [
    "English"
  ],
  "research_areas": [
    "T14 Language Modeling (including training, fine-tuning, representation learning, and generation of synthetic data)",
    "T11 Information Extraction, Named Entity Recognition, Relationship Extraction and Event Detection",
    "T18 Text Summarization"
  ],
  "paper_id": "2025.findings-acl.235",
  "acl_url": "https://aclanthology.org/2025.findings-acl.235/"
}