{
  "title": "“Killing Me” Is Not a Spoiler: Spoiler Detection Model using Graph Neural Networks with Dependency Relation-Aware Attention Mechanism",
  "authors": [
    "Buru Chang",
    "Inggeol Lee",
    "Hyunjae Kim",
    "Jaewoo Kang"
  ],
  "languages": [
    "English"
  ],
  "research_areas": [
    "T21 Parsing, Tagging, Chunking, Grammar, Syntax, Morphosyntax, Morphology",
    "T20 Opinion & Argument Mining, Offensive Language/ Hate speech/ Toxic Language Detection, Sentiment Analysis, Emotion Recognition/Generation"
  ],
  "paper_id": "2021.eacl-main.315",
  "acl_url": "https://aclanthology.org/2021.eacl-main.315/"
}