{
  "title": "A Major Wordnet for a Minority Language: Scottish Gaelic",
  "authors": [
    "Gábor Bella",
    "Fiona McNeill",
    "Rody Gorman",
    "Caoimhín Ó Donnaile",
    "Kirsty Macdonald",
    "Yamini Chandrashekar",
    "Abed Alhakim Freihat",
    "Fausto Giunchiglia"
  ],
  "languages": [
    "English",
    "Scottish Gaelic"
  ],
  "research_areas": [
    "T15 Lexicon and Semantics",
    "T16 Machine Translation (including Speech-to-Speech) and Translation Aids",
    "T13 Knowledge discovery/representation (knowledge graphs, linked data, terminologies, lexicons, ontologies, etc.)"
  ],
  "paper_id": "2020.lrec-1.342",
  "acl_url": "https://aclanthology.org/2020.lrec-1.342/"
}