{
  "title": "Inferring Social Media Users' Mental Health Status from Multimodal Information",
  "authors": [
    "Zhentao Xu",
    "Verónica Pérez-Rosas",
    "Rada Mihalcea"
  ],
  "languages": [
    "English"
  ],
  "research_areas": [
    "T26 Clinical/biomedical NLP, NLP for Mental Health and Wellbeing",
    "T17 Multimodality, Cross-modality (including Sign Languages, Vision and Other Modalities), Multimodal Applications, Grounded Language Acquisition",
    "T23 Social Media Processing"
  ],
  "paper_id": "2020.lrec-1.772",
  "acl_url": "https://aclanthology.org/2020.lrec-1.772/"
}