{
  "title": "Dataset Creation and Evaluation of Aspect Based Sentiment Analysis in Telugu, a Low Resource Language",
  "authors": [
    "Regatte Yashwanth Reddy",
    "Gangula Rama Rohit Reddy",
    "Radhika Mamidi"
  ],
  "languages": [
    "Telugu"
  ],
  "research_areas": [
    "T20 Opinion & Argument Mining, Offensive Language/ Hate speech/ Toxic Language Detection, Sentiment Analysis, Emotion Recognition/Generation"
  ],
  "paper_id": "2020.lrec-1.617",
  "acl_url": "https://aclanthology.org/2020.lrec-1.617/"
}