{
  "title": "A Multilingual Evaluation Dataset for Monolingual Word Sense Alignment",
  "authors": [
    "Sina Ahmadi",
    "John P. McCrae",
    "Sanni Nimb",
    "Fahad Khan",
    "Monica Monachini",
    "Bolette S. Pedersen",
    "Thierry Declerck",
    "Tanja Wissik",
    "Andrea Bellandi",
    "Irene Pisani",
    "Thomas Troelsgaard",
    "Sussi Olsen",
    "Simon Krek",
    "Veronika Lipp",
    "Tamás Váradi",
    "László Simon",
    "András Györfy",
    "Carole Tiberius",
    "Tanneke Schoonheim",
    "Yifat Ben Moshe",
    "Maya Rudich",
    "Raya Abu Ahmad",
    "Dorielle Lonke",
    "Kira Kovalenko",
    "Margit Langemets",
    "Jelena Kallas",
    "Oksana Dereza",
    "Theodorus Fransen",
    "David Cillessen",
    "Mikel Alonso",
    "Ana Salgado",
    "José Luis Sancho",
    "Rafael-J. Ureña-Ruiz",
    "Jordi Porta Zamorano",
    "Kiril Simov",
    "Petya Osenova",
    "Zara Kancheva",
    "Ivaylo Radev",
    "Ranka Stanković",
    "Andrej Perdih",
    "Dejan Gabrovšek"
  ],
  "languages": [
    "Basque",
    "Bulgarian",
    "Danish",
    "Dutch",
    "English",
    "Estonian",
    "German",
    "Hungarian",
    "Irish",
    "Italian",
    "Serbian",
    "Slovenian",
    "Spanish",
    "Portuguese",
    "Russian"
  ],
  "research_areas": [
    "T15 Lexicon and Semantics",
    "T08 Evaluation, Validation, Quality Assurance and Benchmarking Methodologies"
  ],
  "paper_id": "2020.lrec-1.395",
  "acl_url": "https://aclanthology.org/2020.lrec-1.395/"
}