{
  "title": "Token-based Decision Criteria Are Suboptimal in In-context Learning",
  "authors": [
    "Hakaze Cho",
    "Yoshihiro Sakai",
    "Mariko Kato",
    "Kenshiro Tanaka",
    "Akira Ishii",
    "Naoya Inoue"
  ],
  "languages": [
    "English"
  ],
  "research_areas": [
    "T14 Language Modeling",
    "T20 Opinion & Argument Mining, Offensive Language/ Hate speech/ Toxic Language Detection, Sentiment Analysis, Emotion Recognition/Generation",
    "T08 Evaluation, Validation, Quality Assurance and Benchmarking Methodologies"
  ],
  "paper_id": "2025.naacl-long.278",
  "acl_url": "https://aclanthology.org/2025.naacl-long.278/"
}