{
  "title": "VisCGEC: Benchmarking the Visual Chinese Grammatical Error Correction",
  "authors": [
    "Xiaoman Wang",
    "Dan Yuan",
    "Xin Liu",
    "Yike Zhao",
    "Xiaoxiao Zhang",
    "Xizhi Chen",
    "Yunshi Lan"
  ],
  "languages": [
    "Chinese"
  ],
  "research_areas": [
    "T29 NLP for education, Automated essay scoring and feedback generation, grammatical error correction and detection, intelligent tutoring systems",
    "T17 Multimodality, Cross-modality (including Sign Languages, Vision and Other Modalities), Multimodal Applications, Grounded Language Acquisition",
    "T08 Evaluation, Validation, Quality Assurance and Benchmarking Methodologies"
  ],
  "paper_id": "2025.naacl-long.261",
  "acl_url": "https://aclanthology.org/2025.naacl-long.261/"
}