{
  "title": "Improving Vietnamese-English Cross-Lingual Retrieval for Legal and General Domains",
  "authors": [
    "Toan Ngoc Nguyen",
    "Nam Le Hai",
    "Nguyen Doan Hieu",
    "Dai An Nguyen",
    "Linh Ngo Van",
    "Thien Huu Nguyen",
    "Sang Dinh"
  ],
  "languages": [
    "Vietnamese",
    "English"
  ],
  "research_areas": [
    "T06 Information Retrieval and Cross-lingual Retrieval",
    "T25 Legal NLP"
  ],
  "paper_id": "2025.naacl-short.12",
  "acl_url": "https://aclanthology.org/2025.naacl-short.12/"
}