{
  "title": "Enhancing Multilingual Language Model with Massive Multilingual Knowledge Triples",
  "authors": [
    "Linlin Liu",
    "Xin Li",
    "Ruidan He",
    "Lidong Bing",
    "Shafiq Joty",
    "Luo Si"
  ],
  "languages": [
    "English",
    "French",
    "German",
    "Spanish",
    "Italian",
    "Japanese",
    "Korean",
    "Chinese",
    "Vietnamese",
    "Portuguese"
  ],
  "research_areas": [
    "T13 Knowledge discovery/representation (knowledge graphs, linked data, terminologies, lexicons, ontologies, etc.)",
    "T14 Language Modeling (including training, fine-tuning, representation learning, and generation of synthetic data)",
    "T11 Information Extraction, Named Entity Recognition, Relationship Extraction and Event Detection"
  ],
  "paper_id": "2022.emnlp-main.462",
  "acl_url": "https://aclanthology.org/2022.emnlp-main.462/"
}