{
  "title": "A Dataset for Hyper-Relational Extraction and a Cube-Filling Approach",
  "authors": [
    "Yew Ken Chia",
    "Lidong Bing",
    "Sharifah Mahani Aljunied",
    "Luo Si",
    "Soujanya Poria"
  ],
  "languages": [
    "English"
  ],
  "research_areas": [
    "T11 Information Extraction, Named Entity Recognition, Relationship Extraction and Event Detection",
    "T13 Knowledge discovery/representation (knowledge graphs, linked data, terminologies, lexicons, ontologies, etc.)"
  ],
  "paper_id": "2022.emnlp-main.688",
  "acl_url": "https://aclanthology.org/2022.emnlp-main.688/"
}