{
  "title": "Kernel-Whitening: Overcome Dataset Bias with Isotropic Sentence Embedding",
  "authors": [
    "Songyang Gao",
    "Shihan Dou",
    "Qi Zhang",
    "Xuanjing Huang"
  ],
  "languages": [
    "English"
  ],
  "research_areas": [
    "T01 Bias, Guardrails, filters",
    "T14 Language Modeling (including training, fine-tuning, representation learning, and generation of synthetic data)"
  ],
  "paper_id": "2022.emnlp-main.275",
  "acl_url": "https://aclanthology.org/2022.emnlp-main.275/"
}