{
  "title": "Enhancing Self-Consistency and Performance of Pre-Trained Language Models through Natural Language Inference",
  "authors": [
    "Eric Mitchell",
    "Joseph J. Noh",
    "Siyan Li",
    "William S. Armstrong",
    "Ananth Agarwal",
    "Patrick Liu",
    "Chelsea Finn",
    "Christopher D. Manning"
  ],
  "languages": [
    "English"
  ],
  "research_areas": [
    "T10 Question Answering, Open-domain question answering, closed-domain question answering, extractive and abstractive QA, multi-hop question answering",
    "T14 Language Modeling (including training, fine-tuning, representation learning, and generation of synthetic data)",
    "T09 Inference and Reasoning"
  ],
  "paper_id": "2022.emnlp-main.115",
  "acl_url": "https://aclanthology.org/2022.emnlp-main.115/"
}