{
  "title": "Joint Completion and Alignment of Multilingual Knowledge Graphs",
  "authors": [
    "Soumen Chakrabarti",
    "Harkanwar Singh",
    "Shubham Lohiya",
    "Prachi Jain",
    "Mausam"
  ],
  "languages": [
    "English",
    "Spanish",
    "French",
    "Japanese",
    "Greek"
  ],
  "research_areas": [
    "T13 Knowledge discovery/representation (knowledge graphs, linked data, terminologies, lexicons, ontologies, etc.)",
    "T16 Machine Translation (including Speech-to-Speech) and Translation Aids",
    "T08 Evaluation, Validation, Quality Assurance and Benchmarking Methodologies"
  ],
  "paper_id": "2022.emnlp-main.817",
  "acl_url": "https://aclanthology.org/2022.emnlp-main.817/"
}