{
  "title": "Automatic Comment Generation for Chinese Student Narrative Essays",
  "authors": [
    "Zhixin Zhang",
    "Jian Guan",
    "Guowei Xu",
    "Yixiang Tian",
    "Minlie Huang"
  ],
  "languages": [
    "Chinese"
  ],
  "research_areas": [
    "T29 NLP for education, Automated essay scoring and feedback generation, grammatical error correction and detection, intelligent tutoring systems"
  ],
  "paper_id": "2022.emnlp-demos.21",
  "acl_url": "https://aclanthology.org/2022.emnlp-demos.21/"
}